imdex/Captioner.py
imdex/Indexer.py
imdex/__init__.py
imdex/loader.py
imdex/data/__init__.py
imdex-0.2.0.dist-info/METADATA
imdex-0.2.0.dist-info/WHEEL
imdex-0.2.0.dist-info/top_level.txt
imdex-0.2.0.dist-info/RECORD
