Metadata-Version: 2.1
Name: imdex
Version: 0.2.0
Summary: Imdex is a library that allows semantic searches over images sets
Home-page: https://github.com/Lucasfrota/imdex
Author: Lucas Frota
Author-email: lucv.frota@gmail.com
License: UNKNOWN
Platform: UNKNOWN
Classifier: Programming Language :: Python :: 3
Classifier: Operating System :: OS Independent
Requires-Dist: pandas
Requires-Dist: numpy
Requires-Dist: pickle-mixin
Requires-Dist: tensorflow
Requires-Dist: pyemd
Requires-Dist: googledrivedownloader
